mbsync_watcher/__init__.py
mbsync_watcher/config.py
mbsync_watcher/main.py
mbsync_watcher/parse_mbsyncrc.py
mbsync_watcher-0.1.1.data/scripts/mbsync_watcher
mbsync_watcher-0.1.1.dist-info/LICENSE
mbsync_watcher-0.1.1.dist-info/METADATA
mbsync_watcher-0.1.1.dist-info/WHEEL
mbsync_watcher-0.1.1.dist-info/top_level.txt
mbsync_watcher-0.1.1.dist-info/RECORD
