Metadata-Version: 2.1
Name: mbsync-watcher
Version: 0.1.1
Summary: Watch mailboxes using IDLE and sync with mbsync.
Home-page: UNKNOWN
Author: Albert Kim
Author-email: alkim@alkim.org
License: UNKNOWN
Platform: UNKNOWN
Requires-Dist: pyyaml
Requires-Dist: aioimaplib
